README.txt
setup.cfg
setup.py
docs/HISTORY.txt
docs/INSTALL.txt
docs/LICENSE.GPL
docs/LICENSE.txt
slc/__init__.py
slc.dublettefinder.egg-info/PKG-INFO
slc.dublettefinder.egg-info/SOURCES.txt
slc.dublettefinder.egg-info/dependency_links.txt
slc.dublettefinder.egg-info/entry_points.txt
slc.dublettefinder.egg-info/namespace_packages.txt
slc.dublettefinder.egg-info/not-zip-safe
slc.dublettefinder.egg-info/requires.txt
slc.dublettefinder.egg-info/top_level.txt
slc/dublettefinder/__init__.py
slc/dublettefinder/config.py
slc/dublettefinder/configure.zcml
slc/dublettefinder/interfaces.py
slc/dublettefinder/profiles.zcml
slc/dublettefinder/refresh.txt
slc/dublettefinder/setuphandlers.py
slc/dublettefinder/utils.py
slc/dublettefinder/validators.py
slc/dublettefinder/version.txt
slc/dublettefinder/browser/__init__.py
slc/dublettefinder/browser/config.py
slc/dublettefinder/browser/configure.zcml
slc/dublettefinder/browser/queries.py
slc/dublettefinder/browser/portlets/__init__.py
slc/dublettefinder/browser/portlets/configure.zcml
slc/dublettefinder/browser/portlets/possible_dupes.pt
slc/dublettefinder/browser/portlets/possible_dupes.py
slc/dublettefinder/docs/README.txt
slc/dublettefinder/extensions/__init__.py
slc/dublettefinder/extensions/configure.zcml
slc/dublettefinder/extensions/file.py
slc/dublettefinder/model/archgenxml.conf
slc/dublettefinder/model/dublette.zargo
slc/dublettefinder/profiles/default/actionicons.xml
slc/dublettefinder/profiles/default/browserlayer.xml
slc/dublettefinder/profiles/default/catalog.xml
slc/dublettefinder/profiles/default/controlpanel.xml
slc/dublettefinder/profiles/default/cssregistry.xml
slc/dublettefinder/profiles/default/dublettefinder_marker.txt
slc/dublettefinder/profiles/default/factorytool.xml
slc/dublettefinder/profiles/default/import_steps.xml
slc/dublettefinder/profiles/default/jsregistry.xml
slc/dublettefinder/profiles/default/metadata.xml
slc/dublettefinder/profiles/default/portlets.xml
slc/dublettefinder/profiles/default/skins.xml
slc/dublettefinder/profiles/default/types.xml
slc/dublettefinder/skins/dublettefinder_templates/dublettefinder_field.pt
slc/dublettefinder/skins/dublettefinder_templates/dublettefinder_file.pt
slc/dublettefinder/skins/dublettefinder_templates/dublettefinder_string.pt
slc/dublettefinder/tests/__init__.py
slc/dublettefinder/tests/base.py
