Metadata-Version: 1.0
Name: slc.dublettefinder
Version: 0.3.1
Summary: The goal of slc.dublettefinder is to find duplicate files (dublettes ;) in the ZODB and then warn the user via validation error during content edit/creation.
Home-page: http://plone.org/products/slc.dublettefinder/
Author: JC Brand, Syslab.com GmbH
Author-email: brand@syslab.com
License: GPL
Keywords: dublettefinder dublette duplications
Platform: UNKNOWN
Classifier: Framework :: Plone
Classifier: Programming Language :: Python
Classifier: Topic :: Software Development :: Libraries :: Python Modules
Classifier: License :: OSI Approved :: GNU General Public License (GPL)
